FastQuantileLayer/FastQuantileLayer.py
FastQuantileLayer/FastQuantileLayer_new.py
FastQuantileLayer/FixedBinInterpolator.py
FastQuantileLayer/__init__.py
FastQuantileLayer-0.2.1.dist-info/LICENSE
FastQuantileLayer-0.2.1.dist-info/METADATA
FastQuantileLayer-0.2.1.dist-info/WHEEL
FastQuantileLayer-0.2.1.dist-info/top_level.txt
FastQuantileLayer-0.2.1.dist-info/RECORD
