Metadata-Version: 2.1
Name: FastQuantileLayer
Version: 0.2.1
Summary: Keras Layer to apply Quantile transform and its inverse
Home-page: https://github.com/landerli/FastQuantileLayer
Author: Lucio Anderlini
Author-email: l.anderlini@gmail.com
License: UNKNOWN
Platform: UNKNOWN
Classifier: Programming Language :: Python
Classifier: License :: OSI Approved :: MIT License
Classifier: Operating System :: OS Independent
